odoo10_addon_mrp_repair_calendar_view-10.0.1.0.0-py2.7-nspkg.pth
odoo/addons/mrp_repair_calendar_view/README.rst
odoo/addons/mrp_repair_calendar_view/__init__.py
odoo/addons/mrp_repair_calendar_view/__manifest__.py
odoo/addons/mrp_repair_calendar_view/i18n/it.po
odoo/addons/mrp_repair_calendar_view/models/__init__.py
odoo/addons/mrp_repair_calendar_view/models/mrp_repair.py
odoo/addons/mrp_repair_calendar_view/static/description/icon.png
odoo/addons/mrp_repair_calendar_view/views/mrp_repair_view.xml
odoo10_addon_mrp_repair_calendar_view-10.0.1.0.0.dist-info/DESCRIPTION.rst
odoo10_addon_mrp_repair_calendar_view-10.0.1.0.0.dist-info/METADATA
odoo10_addon_mrp_repair_calendar_view-10.0.1.0.0.dist-info/RECORD
odoo10_addon_mrp_repair_calendar_view-10.0.1.0.0.dist-info/WHEEL
odoo10_addon_mrp_repair_calendar_view-10.0.1.0.0.dist-info/metadata.json
odoo10_addon_mrp_repair_calendar_view-10.0.1.0.0.dist-info/namespace_packages.txt
odoo10_addon_mrp_repair_calendar_view-10.0.1.0.0.dist-info/top_level.txt
